ttskit/__init__.py
ttskit/cli_api.py
ttskit/core.py
ttskit/http_server.py
ttskit/makefile.py
ttskit/requirements.txt
ttskit/sdk_api.py
ttskit/web_api.py
ttskit/encoder/__init__.py
ttskit/encoder/audio.py
ttskit/encoder/config.py
ttskit/encoder/inference.py
ttskit/encoder/model.py
ttskit/encoder/params_data.py
ttskit/encoder/params_model.py
ttskit/encoder/preprocess.py
ttskit/encoder/train.py
ttskit/encoder/visualizations.py
ttskit/encoder/data_objects/__init__.py
ttskit/encoder/data_objects/random_cycler.py
ttskit/encoder/data_objects/speaker.py
ttskit/encoder/data_objects/speaker_batch.py
ttskit/encoder/data_objects/speaker_verification_dataset.py
ttskit/encoder/data_objects/utterance.py
ttskit/melgan/__init__.py
ttskit/melgan/hubconf.py
ttskit/melgan/inference.py
ttskit/melgan/preprocess.py
ttskit/melgan/trainer.py
ttskit/melgan/datasets/__init__.py
ttskit/melgan/datasets/dataloader.py
ttskit/melgan/model/__init__.py
ttskit/melgan/model/discriminator.py
ttskit/melgan/model/generator.py
ttskit/melgan/model/identity.py
ttskit/melgan/model/multiscale.py
ttskit/melgan/model/res_stack.py
ttskit/melgan/utils/__init__.py
ttskit/melgan/utils/audio_processing.py
ttskit/melgan/utils/hparams.py
ttskit/melgan/utils/plotting.py
ttskit/melgan/utils/stft.py
ttskit/melgan/utils/train.py
ttskit/melgan/utils/utils.py
ttskit/melgan/utils/validation.py
ttskit/melgan/utils/writer.py
ttskit/mellotron/__init__.py
ttskit/mellotron/audio_processing.py
ttskit/mellotron/data_utils.py
ttskit/mellotron/distributed.py
ttskit/mellotron/fp16_optimizer.py
ttskit/mellotron/hparams.py
ttskit/mellotron/inference.py
ttskit/mellotron/layers.py
ttskit/mellotron/logger.py
ttskit/mellotron/loss_function.py
ttskit/mellotron/loss_scaler.py
ttskit/mellotron/mellotron_utils.py
ttskit/mellotron/model.py
ttskit/mellotron/modules.py
ttskit/mellotron/multiproc.py
ttskit/mellotron/plotting_utils.py
ttskit/mellotron/preprocess.py
ttskit/mellotron/preprocess_embed.py
ttskit/mellotron/stft.py
ttskit-0.3.8.dist-info/LICENSE
ttskit-0.3.8.dist-info/METADATA
ttskit-0.3.8.dist-info/WHEEL
ttskit-0.3.8.dist-info/entry_points.txt
ttskit-0.3.8.dist-info/top_level.txt
ttskit-0.3.8.dist-info/RECORD
