Metadata-Version: 2.1
Name: ttskit
Version: 0.3.8
Summary: text to speech toolkit
Home-page: https://github.com/KuangDD/ttskit
Author: kuangdd
Author-email: kuangdd@foxmail.com
License: UNKNOWN
Platform: UNKNOWN
Classifier: Intended Audience :: Developers
Classifier: Topic :: Software Development :: Build Tools
Classifier: License :: OSI Approved :: MIT License
Classifier: Programming Language :: Python :: 3.6
Classifier: Programming Language :: Python :: 3.7
Classifier: Programming Language :: Python :: 3.8
Classifier: Operating System :: OS Independent
Requires: aukit
Requires: Flask
Requires: gevent
Requires: librosa
Requires: numpy
Requires: phkit
Requires: pydub
Requires: PyYAML
Requires: requests
Requires: scikit_learn
Requires: scipy
Requires: setproctitle
Requires: tqdm
Requires: Unidecode
Requires: webrtcvad_wheels
Requires-Python: >=3.6
Requires-Dist: aukit
Requires-Dist: Flask
Requires-Dist: gevent
Requires-Dist: librosa
Requires-Dist: numpy
Requires-Dist: phkit
Requires-Dist: pydub
Requires-Dist: PyYAML (<=5.4.1)
Requires-Dist: requests
Requires-Dist: scikit-learn
Requires-Dist: scipy
Requires-Dist: setproctitle
Requires-Dist: tqdm
Requires-Dist: Unidecode
Requires-Dist: webrtcvad-wheels
